LICENSE
MANIFEST.in
README.md
setup.py
topsis_by_arushi/__init__.py
topsis_by_arushi/topsis.py
topsis_by_arushi.egg-info/PKG-INFO
topsis_by_arushi.egg-info/SOURCES.txt
topsis_by_arushi.egg-info/dependency_links.txt
topsis_by_arushi.egg-info/requires.txt
topsis_by_arushi.egg-info/top_level.txt